check.py
heiafr/isc/se/tpchecker/__init__.py
heiafr/isc/se/tpchecker/checkdoc.py
heiafr/isc/se/tpchecker/checkgit.py
heiafr/isc/se/tpchecker/command.py
heiafr/isc/se/tpchecker/css/materialize.css
heiafr/isc/se/tpchecker/css/pure-nr.css
heiafr/isc/se/tpchecker/css/style.css
heiafr/isc/se/tpchecker/templates/report.html
heiafr.isc.se.tpchecker-1.0.6.dist-info/LICENSE
heiafr.isc.se.tpchecker-1.0.6.dist-info/METADATA
heiafr.isc.se.tpchecker-1.0.6.dist-info/WHEEL
heiafr.isc.se.tpchecker-1.0.6.dist-info/entry_points.txt
heiafr.isc.se.tpchecker-1.0.6.dist-info/top_level.txt
heiafr.isc.se.tpchecker-1.0.6.dist-info/RECORD
